Metadata-Version: 2.1
Name: irsc
Version: 0.0.1
Summary: An earthquake data package
Home-page: https://github.com/ArminDadras
Author: Armin Dadras Eslamlou
Author-email: armindadraseslamlou@gmail.com
License: UNKNOWN
Platform: UNKNOWN
Classifier: Programming Language :: Python :: 3
Classifier: License :: OSI Approved :: MIT License
Classifier: Operating System :: OS Independent
Requires-Python: >=3.6
